README.rst
setup.py
wishbone_encode_graphite/__init__.py
wishbone_encode_graphite/graphite.py
wishbone_encode_graphite.egg-info/PKG-INFO
wishbone_encode_graphite.egg-info/SOURCES.txt
wishbone_encode_graphite.egg-info/dependency_links.txt
wishbone_encode_graphite.egg-info/entry_points.txt
wishbone_encode_graphite.egg-info/namespace_packages.txt
wishbone_encode_graphite.egg-info/not-zip-safe
wishbone_encode_graphite.egg-info/requires.txt
wishbone_encode_graphite.egg-info/top_level.txt