Metadata-Version: 1.1
Name: wishbone-encode-graphite
Version: 1.0.0
Summary: A Wishbone encode module to convert the Wishbone metric format to Graphite.
Home-page: https://github.com/smetj/wishbone-encode-graphite
Author: Jelle Smet
Author-email: development@smetj.net
License: UNKNOWN
Download-URL: https://github.com/smetj/wishbone-encode-graphite/tarball/master
Platform: Linux
Classifier: Development Status :: 5 - Production/Stable
Classifier: License :: OSI Approved :: GNU General Public License v3 or later (GPLv3+)
Classifier: Programming Language :: Python
Classifier: Programming Language :: Python :: 2.7
Classifier: Programming Language :: Python :: Implementation :: PyPy
Classifier: Intended Audience :: Developers
Classifier: Intended Audience :: System Administrators
